pyrocketmodbus/__init__.py
pyrocketmodbus/pyrm.py
pyrocketmodbus-1.2.2.dist-info/METADATA
pyrocketmodbus-1.2.2.dist-info/WHEEL
pyrocketmodbus-1.2.2.dist-info/licenses/LICENSE
pyrocketmodbus-1.2.2.dist-info/RECORD
