Metadata-Version: 2.4
Name: pyrocketmodbus
Version: 1.2.2
Summary: Python package for Modbus communication
Project-URL: Homepage, https://github.com/ciuliene/pyrocketmodbus
Project-URL: Issues, https://github.com/ciuliene/pyrocketmodbus/issues
Author-email: Giuliano Errico <errgioul2@gmail.com>
License-File: LICENSE
Classifier: License :: OSI Approved :: MIT License
Classifier: Operating System :: OS Independent
Classifier: Programming Language :: Python :: 3
Requires-Python: >=3.11
Requires-Dist: pyserial==3.5
